youtils/__init__.py
youtils/command_line.py
youtils-0.0.1.dist-info/METADATA
youtils-0.0.1.dist-info/WHEEL
youtils-0.0.1.dist-info/entry_points.txt
youtils-0.0.1.dist-info/top_level.txt
youtils-0.0.1.dist-info/RECORD
